tokeks/__init__.py
tokeks-0.1.1.dist-info/LICENSE
tokeks-0.1.1.dist-info/METADATA
tokeks-0.1.1.dist-info/WHEEL
tokeks-0.1.1.dist-info/top_level.txt
tokeks-0.1.1.dist-info/RECORD
