Metadata-Version: 2.1
Name: tokeks
Version: 0.1.1
Summary: UNKNOWN
Home-page: https://github.com/ckarageorgkaneen/tokeks
License: MIT
Project-URL: Tracker, https://github.com/ckarageorgkaneen/tokeks/issues
Project-URL: Source, https://github.com/ckarageorgkaneen/tokeks
Platform: UNKNOWN
Classifier: Development Status :: 5 - Production/Stable
Classifier: Programming Language :: Python
Classifier: Programming Language :: Python :: 3.5
Classifier: Programming Language :: Python :: 3.6
Classifier: Programming Language :: Python :: 3.7
Classifier: Programming Language :: Python :: 3.8
Classifier: Programming Language :: Python :: 3.9
Classifier: Intended Audience :: Developers
Classifier: Operating System :: POSIX :: Linux
Classifier: License :: OSI Approved :: MIT License
Classifier: Topic :: Software Development :: Libraries
Requires-Python: >=3.5
License-File: LICENSE
